Encorsa_e_Factura/AnafUtils.py
Encorsa_e_Factura/WebConRequestUtils.py
Encorsa_e_Factura/XMLFromTemplateBuilder.py
Encorsa_e_Factura/XMLUtils.py
Encorsa_e_Factura/__init__.py
Encorsa_e_Factura/descarcaRaspunsIncarcareFactura.py
Encorsa_e_Factura/runLocaly.py
Encorsa_e_Factura/sendInvoiceANAF.py
Encorsa_e_Factura/sincronizare.py
Encorsa_e_Factura/verificareStatusFacturaTrimisa.py
Encorsa_e_Factura/xml_namespaces.py
encorsa_e_factura-0.4.8.dist-info/licenses/LICENCE
encorsa_e_factura-0.4.8.dist-info/METADATA
encorsa_e_factura-0.4.8.dist-info/WHEEL
encorsa_e_factura-0.4.8.dist-info/entry_points.txt
encorsa_e_factura-0.4.8.dist-info/top_level.txt
encorsa_e_factura-0.4.8.dist-info/RECORD
