Metadata-Version: 2.4
Name: Encorsa_e_Factura
Version: 0.4.8
Summary: A small example package
Home-page: https://encorsa.ro
Author: Dan Popescu, Razvan Ogrezeanu
Author-email: dan.popescu@encorsa.com, razvan.ogrezeanu@encorsa.com
Classifier: Programming Language :: Python :: 3
Classifier: License :: OSI Approved :: MIT License
Classifier: Operating System :: OS Independent
Requires-Python: >=3.8
License-File: LICENCE
Requires-Dist: requests
Dynamic: license-file
